dayu_widgets_tag/__init__.py
dayu_widgets_tag/__version__.py
dayu_widgets_tag/checkable_tag.py
dayu_widgets_tag/new_tag.py
dayu_widgets_tag/tag.py
dayu_widgets_tag-0.2.0.dist-info/LICENSE
dayu_widgets_tag-0.2.0.dist-info/WHEEL
dayu_widgets_tag-0.2.0.dist-info/METADATA
dayu_widgets_tag-0.2.0.dist-info/RECORD
