Metadata-Version: 2.1
Name: dayu-widgets-tag
Version: 0.2.0
Summary: Tag component for dayu_widgets as a plugin
Home-page: https://github.com/muyr/dayu_widgets_tag
License: MIT
Keywords: PySide,PyQt,UI,PySide2,PyQt5,Tag
Author: Yanru Mu 
Author-email: muyanru345@163.com
Requires-Python: >=2.7, !=3.0.*, !=3.1.*, !=3.2.*, !=3.3.*, !=3.4.*, !=3.5.*
Classifier: License :: OSI Approved :: MIT License
Classifier: Programming Language :: Python :: 2
Classifier: Programming Language :: Python :: 2.7
Classifier: Programming Language :: Python :: 3
Classifier: Programming Language :: Python :: 3.5
Classifier: Programming Language :: Python :: 3.6
Classifier: Programming Language :: Python :: 3.7
Classifier: Programming Language :: Python :: 3.8
Classifier: Programming Language :: Python :: 3.9
Requires-Dist: QtPy (>=1.11.3,<2.0.0)
Requires-Dist: dayu_widgets (>=0.9,<0.10)
Project-URL: Documentation, https://muyr.github.io/dayu_widgets_tag/#/
Project-URL: Repository, https://github.com/muyr/dayu_widgets_tag
